Workbook

Sheet Вводные
A1: Модель себестоимости минеральной ваты (без подгонки под таргет)
A2: Все синие поля — ввод пользователя. Чёрные — формулы. Упаковка считается отдельным блоком; её можно включать/выключать в сценариях.
A4: 1) Продукт и производство
A5: Производительность по массе Qm | B5: т/ч | C5: 4
A6: Выход годной продукции Y | B6: доля | C6: 0.97
A7: Доля сухой органики в продукте (LOI) | B7: % масс. | C7: 4.5
A8: Цена смолы (как поставляется) | B8: руб/т | C8: 60000
A9: Сухой остаток смолы S | B9: доля | C9: 0.5
A10: Эффективность нанесения η | B10: доля | C10: 0.95
A11: Доля сухой органики x_org | B11: доля | C11: =C7/100
A13: 2) Затраты (вводная структура)
A14: 2.1 Постоянные/условно‑постоянные (руб/ч) | E14: 2.2 Переменные на тонну (руб/т)
A15: ФОТ производства (смена) | B15: руб/ч | C15: 35000 | E15: Шихта/сырьё без смолы | F15: руб/т | G15: 18000
A16: Цеховые накладные | B16: руб/ч | C16: 20000 | E16: Энергия (газ+электро) | F16: руб/т | G16: 12000
A17: Ремонт/обслуживание (пул) | B17: руб/ч | C17: 8000 | E17: Расходники на выпуск | F17: руб/т | G17: 2500
A18: Амортизация/лизинг | B18: руб/ч | C18: 12000 | E18: Прочие переменные | F18: руб/т | G18: 1000
A19: Прочие фиксированные | B19: руб/ч | C19: 5000 | E19: ИТОГО переменные (без смолы) | G19: =SUM(G15:G18)
A20: ИТОГО фиксированные | C20: =SUM(C15:C19)
A22: 3) Геометрия плит и упаковка (в пачки)
A23: 3.1 Геометрия | E23: 3.2 Параметры упаковки
A24: Длина плиты L | B24: м | C24: 1.2 | E24: Макс. высота пачки h_pack_max | F24: м | G24: 0.6
A25: Ширина плиты W | B25: м | C25: 0.6 | E25: Макс. масса пачки m_pack_max | F25: кг | G25: 25
A26: Толщина плиты t | B26: м | C26: 0.05 | E26: Макс. высота палеты H_pallet_max | F26: м | G26: 2.4
E27: Высота поддона h_pallet | F27: м | G27: 0.15
E28: Пачек на поддон N_pallet | F28: пачек/поддон | G28: 12
E29: Стоимость плёнки/маркировки | F29: руб/пачка | G29: =Упаковка!F7
E30: Стоимость поддона | F30: руб/поддон | G30: 1500
E31: Обвязка/стрейч палеты | F31: руб/палета | G31: 80
E32: Упаковка: труд | F32: руб/пачка | G32: 0
A34: Объём плиты V_plate | B34: м³ | C34: =C24*C25*C26
A36: 4) Сценарии плотности (ρ)
A37: Плотности (кг/м³) | B37: 50 | C37: 100 | D37: 150 | E37: 200
A39: Примечание по умолчаниям: числа в блоках затрат поставлены как реалистичные заглушки для оценки. Замените их на фактические нормы/цены/учётные данные.

Sheet Себестоимость_т
A1: Себестоимость производства (без упаковки) — расчёт на 1 т товарной ваты
A2: Все входные берутся с листа «Вводные». Здесь показана декомпозиция по блокам и итог.
A4: 1) Смола (расчёт по сухому остатку)
A5: Доля сухой органики x_org | B5: доля | C5: =Вводные!C11
A6: Сухой остаток смолы S | B6: доля | C6: =Вводные!C9
A7: Эффективность нанесения η | B7: доля | C7: =Вводные!C10
A8: Расход смолы (как поставляется) | B8: кг/т | C8: =1000* C5/(C6*C7)
A9: Цена смолы | B9: руб/т | C9: =Вводные!C8
A10: Стоимость смолы | B10: руб/т | C10: =C8/1000*C9
A12: 2) Затраты (по блокам)
A13: Фиксированные затраты | B13: руб/ч | C13: =Вводные!C20 | D13: Переменные (без смолы) | E13: руб/т | F13: =Вводные!G19
A14: Производительность Qm | B14: т/ч | C14: =Вводные!C5 | D14: Смола | E14: руб/т | F14: =C10
A15: Выход годной Y | B15: доля | C15: =Вводные!C6 | D15: Переменные всего | E15: руб/т | F15: =F13+F14
A16: Фиксированные на 1 т (с учётом Y) | B16: руб/т | C16: =C13/C14/C15 | D16: Переменные на 1 т (с учётом Y) | E16: руб/т | F16: =F15/C15
A18: ИТОГО себестоимость производства (без упаковки) | D18: руб/т | E18: =C16+F16
A20: Формула: C_prod_t = (C_fixed_h / Qm)/Y + (C_var_ex + C_resin)/Y

Sheet Сценарии_м3
A1: Сценарии по плотности: пересчёт в руб/м³ и упаковка в пачки
A2: Упаковка как производственный расход считается отдельно. Если нужно считать только «без упаковки» — смотрите колонки C_prod, руб/м³ и C_prod, руб/пачка.
A4: ρ, кг/м³ | B4: t, м | C4: V плиты, м³ | D4: m плиты, кг | E4: Плит/пачка (по высоте) | F4: Плит/пачка (по массе) | G4: Плит/пачка (итог) | H4: h пачки, м | I4: m пачки, кг | J4: V пачки, м³ | K4: Пачек/м³ | L4: Пачек/т | M4: C_prod, руб/т | N4: C_prod, руб/м³ | O4: C_prod, руб/пачка | P4: Упаковка, руб/пачка | Q4: Упаковка, руб/м³ | R4: ИТОГО, руб/м³
A5: =Вводные!B37 | B5: =Вводные!C26 | C5: =Вводные!C24*Вводные!C25*Вводные!C26 | D5: =C5*A5 | E5: =ROUNDDOWN(ROUND(Вводные!G24/B5,6),0) | F5: =ROUNDDOWN(ROUND(Вводные!G25/D5,6),0) | G5: =MAX(1,MIN(E5,F5)) | H5: =G5*B5 | I5: =G5*D5 | J5: =G5*C5 | K5: =1/J5 | L5: =(1000/A5)/J5 | M5: =Себестоимость_т!E18 | N5: =M5*A5/1000 | O5: =N5*J5 | P5: =Упаковка!$F$10 | Q5: =P5*K5 | R5: =N5+Q5
A6: =Вводные!C37 | B6: =Вводные!C26 | C6: =Вводные!C24*Вводные!C25*Вводные!C26 | D6: =C6*A6 | E6: =ROUNDDOWN(ROUND(Вводные!G24/B6,6),0) | F6: =ROUNDDOWN(ROUND(Вводные!G25/D6,6),0) | G6: =MAX(1,MIN(E6,F6)) | H6: =G6*B6 | I6: =G6*D6 | J6: =G6*C6 | K6: =1/J6 | L6: =(1000/A6)/J6 | M6: =Себестоимость_т!E18 | N6: =M6*A6/1000 | O6: =N6*J6 | P6: =Упаковка!$F$10 | Q6: =P6*K6 | R6: =N6+Q6
A7: =Вводные!D37 | B7: =Вводные!C26 | C7: =Вводные!C24*Вводные!C25*Вводные!C26 | D7: =C7*A7 | E7: =ROUNDDOWN(ROUND(Вводные!G24/B7,6),0) | F7: =ROUNDDOWN(ROUND(Вводные!G25/D7,6),0) | G7: =MAX(1,MIN(E7,F7)) | H7: =G7*B7 | I7: =G7*D7 | J7: =G7*C7 | K7: =1/J7 | L7: =(1000/A7)/J7 | M7: =Себестоимость_т!E18 | N7: =M7*A7/1000 | O7: =N7*J7 | P7: =Упаковка!$F$10 | Q7: =P7*K7 | R7: =N7+Q7
A8: =Вводные!E37 | B8: =Вводные!C26 | C8: =Вводные!C24*Вводные!C25*Вводные!C26 | D8: =C8*A8 | E8: =ROUNDDOWN(ROUND(Вводные!G24/B8,6),0) | F8: =ROUNDDOWN(ROUND(Вводные!G25/D8,6),0) | G8: =MAX(1,MIN(E8,F8)) | H8: =G8*B8 | I8: =G8*D8 | J8: =G8*C8 | K8: =1/J8 | L8: =(1000/A8)/J8 | M8: =Себестоимость_т!E18 | N8: =M8*A8/1000 | O8: =N8*J8 | P8: =Упаковка!$F$10 | Q8: =P8*K8 | R8: =N8+Q8
P9: =Упаковка!$F$10
A10: Примечание: «Пачек на поддон N_pallet» задаётся вручную (вводные). Без этой цифры невозможно корректно распределить стоимость поддона/обвязки по пачкам.

Sheet Упаковка
A1: РАСЧЕТ И АНАЛИЗ СТОИМОСТИ УПАКОВКИ
A3: 1. Входные параметры | E3: 2. Расчет себестоимости (на 1 пачку)
A4: Длина плиты, L | B4: мм | C4: ='Вводные'!C24*1000 | E4: Высота пачки | F4: =C6*C7 | G4: мм
A5: Ширина плиты, W | B5: мм | C5: ='Вводные'!C25*1000 | E5: Периметр пачки | F5: =2*(C4+C5)/1000 | G5: м
A6: Толщина плиты, t | B6: мм | C6: ='Вводные'!C26*1000 | E6: Площадь пленки на пачку | F6: =F5*(F4/1000) | G6: м2
A7: Кол-во плит в пачке | B7: шт | C7: 12 | E7: Стоимость пленки пачки | F7: =F6*C9 | G7: руб
A8: Пачек на паллете | B8: шт | C8: ='Вводные'!G28 | E8: Доля поддона на пачку | F8: =C10/C8 | G8: руб
A9: Цена пленки | B9: руб/м2 | C9: 100 | E9: Доля пакета на пачку | F9: =C11/C8 | G9: руб
A10: Цена поддона (паллет) | B10: руб/шт | C10: 1500 | E10: ИТОГО упаковка на пачку | F10: =SUM(F7:F9) | G10: руб
A11: Цена большого пакета | B11: руб/шт | C11: 500
A14: 3. Анализ структуры затрат (%) | E14: 4. Сравнение сценариев
A15: Пленка (пачка) | B15: =F7/F10 | E15: Плит | F15: Высота, мм | G15: Пленка, руб | H15: Итого/пачка, руб
A16: Поддон | B16: =F8/F10 | E16: 8 | F16: =E16*C$6 | G16: =(2*($C$4+$C$5)/1000)*(F16/1000)*$C$9 | H16: =G16+($C$10+$C$11)/$C$8
A17: Большой пакет | B17: =F9/F10 | E17: 10 | F17: =E17*C$6 | G17: =(2*($C$4+$C$5)/1000)*(F17/1000)*$C$9 | H17: =G17+($C$10+$C$11)/$C$8
E18: 12 | F18: =E18*C$6 | G18: =(2*($C$4+$C$5)/1000)*(F18/1000)*$C$9 | H18: =G18+($C$10+$C$11)/$C$8
E19: 14 | F19: =E19*C$6 | G19: =(2*($C$4+$C$5)/1000)*(F19/1000)*$C$9 | H19: =G19+($C$10+$C$11)/$C$8
A20: 5. Оптимизация расходов | E20: 16 | F20: =E20*C$6 | G20: =(2*($C$4+$C$5)/1000)*(F20/1000)*$C$9 | H20: =G20+($C$10+$C$11)/$C$8
A21: Целевая высота пачки (мм) | C21: 600
A22: Отклонение от цели | C22: =F4-C21 | E22: 6. Итоговая сводка
A23: Рекомендация | C23: =IF(ABS(C22)>50, "Изменить кол-во плит", "Оптимально") | E23: Стоимость упаковки 1 м3 | G23: =F10/(C4*C5*F4/1000000000)
E24: Упаковка на 1 тонну (100кг) | G24: =G23/0.1
