Workbook

Sheet Вводные
A1: Модель себестоимости минеральной ваты (без подгонки под таргет)
A2: Все синие поля — ввод пользователя. Чёрные — формулы. Упаковка считается отдельным блоком; её можно включать/выключать в сценариях.
A4: 1) Продукт и производство
A5: Производительность по массе Qm | B5: т/ч | C5: 4
A6: Выход годной продукции Y | B6: доля | C6: 0.97
A7: Доля сухой органики в продукте (LOI) | B7: % масс. | C7: 4.5
A8: Цена смолы (как поставляется) | B8: руб/т | C8: 60000
A9: Сухой остаток смолы S | B9: доля | C9: 0.5
A10: Эффективность нанесения η | B10: доля | C10: 0.95
A11: Доля сухой органики x_org | B11: доля | C11: =C7/100 -> 0.045
A13: 2) Затраты (вводная структура)
A14: 2.1 Постоянные/условно‑постоянные (руб/ч) | E14: 2.2 Переменные на тонну (руб/т)
A15: ФОТ производства (смена) | B15: руб/ч | C15: 35000 | E15: Шихта/сырьё без смолы | F15: руб/т | G15: 18000
A16: Цеховые накладные | B16: руб/ч | C16: 20000 | E16: Энергия (газ+электро) | F16: руб/т | G16: 12000
A17: Ремонт/обслуживание (пул) | B17: руб/ч | C17: 8000 | E17: Расходники на выпуск | F17: руб/т | G17: 2500
A18: Амортизация/лизинг | B18: руб/ч | C18: 12000 | E18: Прочие переменные | F18: руб/т | G18: 1000
A19: Прочие фиксированные | B19: руб/ч | C19: 5000 | E19: ИТОГО переменные (без смолы) | G19: =SUM(G15:G18) -> 33500
A20: ИТОГО фиксированные | C20: =SUM(C15:C19) -> 80000
A22: 3) Геометрия плит и упаковка (в пачки)
A23: 3.1 Геометрия | E23: 3.2 Параметры упаковки
A24: Длина плиты L | B24: м | C24: 1.2 | E24: Макс. высота пачки h_pack_max | F24: м | G24: 0.6
A25: Ширина плиты W | B25: м | C25: 0.6 | E25: Макс. масса пачки m_pack_max | F25: кг | G25: 25
A26: Толщина плиты t | B26: м | C26: 0.05 | E26: Макс. высота палеты H_pallet_max | F26: м | G26: 2.4
E27: Высота поддона h_pallet | F27: м | G27: 0.15
E28: Пачек на поддон N_pallet | F28: пачек/поддон | G28: 12
E29: Стоимость плёнки/маркировки | F29: руб/пачка | G29: 35
E30: Стоимость поддона | F30: руб/поддон | G30: 350
E31: Обвязка/стрейч палеты | F31: руб/палета | G31: 80
E32: Упаковка: труд | F32: руб/пачка | G32: 0
A34: Объём плиты V_plate | B34: м³ | C34: =C24*C25*C26 -> 0.036
A36: 4) Сценарии плотности (ρ)
A37: Плотности (кг/м³) | B37: 50 | C37: 100 | D37: 150 | E37: 200
A39: Примечание по умолчаниям: числа в блоках затрат поставлены как реалистичные заглушки для оценки. Замените их на фактические нормы/цены/учётные данные.

Sheet Себестоимость_т
A1: Себестоимость производства (без упаковки) — расчёт на 1 т товарной ваты
A2: Все входные берутся с листа «Вводные». Здесь показана декомпозиция по блокам и итог.
A4: 1) Смола (расчёт по сухому остатку)
A5: Доля сухой органики x_org | B5: доля | C5: =Вводные!C11 -> 0.045
A6: Сухой остаток смолы S | B6: доля | C6: =Вводные!C9 -> 0.5
A7: Эффективность нанесения η | B7: доля | C7: =Вводные!C10 -> 0.95
A8: Расход смолы (как поставляется) | B8: кг/т | C8: =1000* C5/(C6*C7) -> 94.736842
A9: Цена смолы | B9: руб/т | C9: =Вводные!C8 -> 60000
A10: Стоимость смолы | B10: руб/т | C10: =C8/1000*C9 -> 5684.2105
A12: 2) Затраты (по блокам)
A13: Фиксированные затраты | B13: руб/ч | C13: =Вводные!C20 -> 80000 | D13: Переменные (без смолы) | E13: руб/т | F13: =Вводные!G19 -> 33500
A14: Производительность Qm | B14: т/ч | C14: =Вводные!C5 -> 4 | D14: Смола | E14: руб/т | F14: =C10 -> 5684.2105
A15: Выход годной Y | B15: доля | C15: =Вводные!C6 -> 0.97 | D15: Переменные всего | E15: руб/т | F15: =F13+F14 -> 39184.211
A16: Фиксированные на 1 т (с учётом Y) | B16: руб/т | C16: =C13/C14/C15 -> 20618.557 | D16: Переменные на 1 т (с учётом Y) | E16: руб/т | F16: =F15/C15 -> 40396.093
A18: ИТОГО себестоимость производства (без упаковки) | D18: руб/т | E18: =C16+F16 -> 61014.65
A20: Формула: C_prod_t = (C_fixed_h / Qm)/Y + (C_var_ex + C_resin)/Y

Sheet Сценарии_м3
A1: Сценарии по плотности: пересчёт в руб/м³ и упаковка в пачки
A2: Упаковка как производственный расход считается отдельно. Если нужно считать только «без упаковки» — смотрите колонки C_prod, руб/м³ и C_prod, руб/пачка.
A4: ρ, кг/м³ | B4: t, м | C4: V плиты, м³ | D4: m плиты, кг | E4: Плит/пачка (по высоте) | F4: Плит/пачка (по массе) | G4: Плит/пачка (итог) | H4: h пачки, м | I4: m пачки, кг | J4: V пачки, м³ | K4: Пачек/м³ | L4: Пачек/т | M4: C_prod, руб/т | N4: C_prod, руб/м³ | O4: C_prod, руб/пачка | P4: Упаковка, руб/пачка | Q4: Упаковка, руб/м³ | R4: ИТОГО, руб/м³
A5: =Вводные!B37 -> 50 | B5: =Вводные!C26 -> 0.05 | C5: =Вводные!C24*Вводные!C25*Вводные!C26 -> 0.036 | D5: =C5*A5 -> 1.8 | E5: =ROUNDDOWN(ROUND(Вводные!G24/B5,6),0) -> 12 | F5: =ROUNDDOWN(ROUND(Вводные!G25/D5,6),0) -> 13 | G5: =MAX(1,MIN(E5,F5)) -> 12 | H5: =G5*B5 -> 0.6 | I5: =G5*D5 -> 21.6 | J5: =G5*C5 -> 0.432 | K5: =1/J5 -> 2.3148148 | L5: =(1000/A5)/J5 -> 46.296296 | M5: =Себестоимость_т!E18 -> 61014.65 | N5: =M5*A5/1000 -> 3050.7325 | O5: =N5*J5 -> 1317.9164 | P5: =Вводные!G29+Вводные!G32+(Вводные!G30+Вводные!G31)/Вводные!G28 -> 70.833333 | Q5: =P5*K5 -> 163.96605 | R5: =N5+Q5 -> 3214.6986
A6: =Вводные!C37 -> 100 | B6: =Вводные!C26 -> 0.05 | C6: =Вводные!C24*Вводные!C25*Вводные!C26 -> 0.036 | D6: =C6*A6 -> 3.6 | E6: =ROUNDDOWN(ROUND(Вводные!G24/B6,6),0) -> 12 | F6: =ROUNDDOWN(ROUND(Вводные!G25/D6,6),0) -> 6 | G6: =MAX(1,MIN(E6,F6)) -> 6 | H6: =G6*B6 -> 0.3 | I6: =G6*D6 -> 21.6 | J6: =G6*C6 -> 0.216 | K6: =1/J6 -> 4.6296296 | L6: =(1000/A6)/J6 -> 46.296296 | M6: =Себестоимость_т!E18 -> 61014.65 | N6: =M6*A6/1000 -> 6101.465 | O6: =N6*J6 -> 1317.9164 | P6: =Вводные!G29+Вводные!G32+(Вводные!G30+Вводные!G31)/Вводные!G28 -> 70.833333 | Q6: =P6*K6 -> 327.9321 | R6: =N6+Q6 -> 6429.3971
A7: =Вводные!D37 -> 150 | B7: =Вводные!C26 -> 0.05 | C7: =Вводные!C24*Вводные!C25*Вводные!C26 -> 0.036 | D7: =C7*A7 -> 5.4 | E7: =ROUNDDOWN(ROUND(Вводные!G24/B7,6),0) -> 12 | F7: =ROUNDDOWN(ROUND(Вводные!G25/D7,6),0) -> 4 | G7: =MAX(1,MIN(E7,F7)) -> 4 | H7: =G7*B7 -> 0.2 | I7: =G7*D7 -> 21.6 | J7: =G7*C7 -> 0.144 | K7: =1/J7 -> 6.9444444 | L7: =(1000/A7)/J7 -> 46.296296 | M7: =Себестоимость_т!E18 -> 61014.65 | N7: =M7*A7/1000 -> 9152.1975 | O7: =N7*J7 -> 1317.9164 | P7: =Вводные!G29+Вводные!G32+(Вводные!G30+Вводные!G31)/Вводные!G28 -> 70.833333 | Q7: =P7*K7 -> 491.89815 | R7: =N7+Q7 -> 9644.0957
A8: =Вводные!E37 -> 200 | B8: =Вводные!C26 -> 0.05 | C8: =Вводные!C24*Вводные!C25*Вводные!C26 -> 0.036 | D8: =C8*A8 -> 7.2 | E8: =ROUNDDOWN(ROUND(Вводные!G24/B8,6),0) -> 12 | F8: =ROUNDDOWN(ROUND(Вводные!G25/D8,6),0) -> 3 | G8: =MAX(1,MIN(E8,F8)) -> 3 | H8: =G8*B8 -> 0.15 | I8: =G8*D8 -> 21.6 | J8: =G8*C8 -> 0.108 | K8: =1/J8 -> 9.2592593 | L8: =(1000/A8)/J8 -> 46.296296 | M8: =Себестоимость_т!E18 -> 61014.65 | N8: =M8*A8/1000 -> 12202.93 | O8: =N8*J8 -> 1317.9164 | P8: =Вводные!G29+Вводные!G32+(Вводные!G30+Вводные!G31)/Вводные!G28 -> 70.833333 | Q8: =P8*K8 -> 655.8642 | R8: =N8+Q8 -> 12858.794
A10: Примечание: «Пачек на поддон N_pallet» задаётся вручную (вводные). Без этой цифры невозможно корректно распределить стоимость поддона/обвязки по пачкам.
